filecoin_address/__init__.py
filecoin_address/address.py
filecoin_address/address_creation.py
filecoin_address/base32.py
filecoin_address/checksum.py
filecoin_address/conversion.py
filecoin_address/encoding.py
filecoin_address/enums.py
filecoin_address/eth_utils.py
filecoin_address/id_address.py
filecoin_address/leb128_utils.py
filecoin_address/py.typed
filecoin_address/validation.py
filecoin_address-0.2.0.dist-info/licenses/LICENSE
filecoin_address-0.2.0.dist-info/METADATA
filecoin_address-0.2.0.dist-info/WHEEL
filecoin_address-0.2.0.dist-info/top_level.txt
filecoin_address-0.2.0.dist-info/RECORD
