Metadata-Version: 2.3
Name: filecoin-address
Version: 0.2.0
Summary: Filecoin address manipulation routines for Python
Author: Filecoin Incentive Design Labs
License: Apache-2.0 OR MIT
Project-URL: Homepage, https://github.com/fidlabs/filecoin-address-python
Project-URL: Repository, https://github.com/fidlabs/filecoin-address-python
Project-URL: Issues, https://github.com/fidlabs/filecoin-address-python/issues
Keywords: filecoin,address
Classifier: Development Status :: 4 - Beta
Classifier: Intended Audience :: Developers
Classifier: License :: OSI Approved :: MIT License
Classifier: Programming Language :: Python :: 3
Classifier: Programming Language :: Python :: 3.7
Classifier: Programming Language :: Python :: 3.8
Classifier: Programming Language :: Python :: 3.9
Classifier: Programming Language :: Python :: 3.10
Classifier: Programming Language :: Python :: 3.11
Classifier: Programming Language :: Python :: 3.12
Classifier: Topic :: Software Development :: Libraries :: Python Modules
Requires-Python: >=3.7
License-File: LICENSE
Requires-Dist: leb128>=1.0.0
Requires-Dist: eth-utils>=2.0.0
Provides-Extra: dev
Requires-Dist: pytest>=7.0.0; extra == "dev"
Requires-Dist: pytest-cov>=4.0.0; extra == "dev"
Dynamic: license-file
